CHANGELOG.txt
LICENSE.txt
MANIFEST.in
README.txt
setup.py
OzBasicCalculator/__init__.py
OzymandiasBasicCalculator.egg-info/PKG-INFO
OzymandiasBasicCalculator.egg-info/SOURCES.txt
OzymandiasBasicCalculator.egg-info/dependency_links.txt
OzymandiasBasicCalculator.egg-info/top_level.txt